querynator/__init__.py
querynator/__main__.py
querynator/helper_functions/__init__.py
querynator/helper_functions/doid.obo
querynator/helper_functions/helper_functions.py
querynator/helper_functions/ontology.py
querynator/query_api/__init__.py
querynator/query_api/cancertypes.js
querynator/query_api/cgi_api.py
querynator/query_api/civic_api.py
querynator/report_scripts/__init__.py
querynator/report_scripts/combine_cgi.py
querynator/report_scripts/combine_cgi_civic.py
querynator/report_scripts/combine_civic.py
querynator/report_scripts/create_report.py
querynator/report_scripts/sort_variants.py
querynator/report_scripts/templates/template_individual.html
querynator/report_scripts/templates/template_overall_plotly_pieplots.html
querynator/report_scripts/templates/template_overall_upsetplots.html
tests/__init__.py
tests/test_ontology.py
tests/test_querynator.py
querynator-0.6.0.dist-info/LICENSE
querynator-0.6.0.dist-info/METADATA
querynator-0.6.0.dist-info/WHEEL
querynator-0.6.0.dist-info/entry_points.txt
querynator-0.6.0.dist-info/top_level.txt
querynator-0.6.0.dist-info/RECORD
