Metadata-Version: 2.1
Name: querynator
Version: 0.6.0
Summary: Python package to query cancer variant databases
Home-page: https://github.com/qbic-pipelines/querynator
Author: Susanne Jodoin, Mark Polster, Niclas Grote
Author-email: susanne.jodoin@qbic.uni-tuebingen.de, mark.polster@uni-tuebingen.de, niclas.grote@student.uni-tuebingen.de
License: MIT license
Keywords: querynator
Classifier: Development Status :: 2 - Pre-Alpha
Classifier: Intended Audience :: Developers
Classifier: License :: OSI Approved :: MIT License
Classifier: Natural Language :: English
Classifier: Programming Language :: Python :: 3
Classifier: Programming Language :: Python :: 3.8
Requires-Python: >=3.8,<3.11
License-File: LICENSE
Requires-Dist: sphinx>=5.3.0
Requires-Dist: sphinx-rtd-theme
Requires-Dist: pytest>=6.2.4
Requires-Dist: click>=8.1.3
Requires-Dist: httplib2
Requires-Dist: requests
Requires-Dist: requests-cache
Requires-Dist: urllib3<2
Requires-Dist: pandas==1.5.3
Requires-Dist: numpy==1.24.4
Requires-Dist: civicpy~=3.0.0
Requires-Dist: pyvcf3~=1.0.3
Requires-Dist: pretty-html-table~=0.9.16
Requires-Dist: matplotlib~=3.6.1
Requires-Dist: upsetplot~=0.8.0
